{"kind":"APIResourceList","apiVersion":"v1","groupVersion":"k3s.cattle.io/v1","resources":[{"name":"addons","singularName":"addon","namespaced":true,"group":"k3s.cattle.io","version":"v1","kind":"Addon","verbs":["delete","deletecollection","get","list","patch","create","update","watch"]},{"name":"etcdsnapshotfiles","singularName":"etcdsnapshotfile","namespaced":false,"group":"k3s.cattle.io","version":"v1","kind":"ETCDSnapshotFile","verbs":["delete","deletecollection","get","list","patch","create","update","watch"]}]}
